loafang/__init__.py
loafang/__main__.py
loafang/_const.py
loafang/_dataclasses.py
loafang/_parsers.py
loafang/main.py
loafang/methods.py
loafang/parser.py
loafang/query.py
loafang/utils.py
loafang-0.2.0.dist-info/LICENSE
loafang-0.2.0.dist-info/METADATA
loafang-0.2.0.dist-info/WHEEL
loafang-0.2.0.dist-info/entry_points.txt
loafang-0.2.0.dist-info/top_level.txt
loafang-0.2.0.dist-info/RECORD
