Metadata-Version: 2.1
Name: loafang
Version: 0.2.0
Summary: A JSON based RESTapi Query Language.
Home-page: https://github.com/Adwaith-Rajesh/loafang
Author: Adwaith-Rajesh
Author-email: adwaithrajesh3180@gmail.com
License: MIT
Platform: UNKNOWN
Classifier: License :: OSI Approved :: MIT License
Classifier: Programming Language :: Python :: 3
Classifier: Programming Language :: Python :: 3 :: Only
Classifier: Programming Language :: Python :: 3.7
Classifier: Programming Language :: Python :: 3.8
Classifier: Programming Language :: Python :: 3.9
Requires-Python: >=3.7.1
License-File: LICENSE
